CHANGES.rst
CONTRIBUTORS.rst
MANIFEST.in
README.rst
setup.cfg
setup.py
docs/LICENSE.GPL
docs/LICENSE.rst
docs/index.rst
src/collective/__init__.py
src/collective.smartlink.egg-info/PKG-INFO
src/collective.smartlink.egg-info/SOURCES.txt
src/collective.smartlink.egg-info/dependency_links.txt
src/collective.smartlink.egg-info/entry_points.txt
src/collective.smartlink.egg-info/namespace_packages.txt
src/collective.smartlink.egg-info/not-zip-safe
src/collective.smartlink.egg-info/requires.txt
src/collective.smartlink.egg-info/top_level.txt
src/collective/smartlink/__init__.py
src/collective/smartlink/configure.zcml
src/collective/smartlink/interfaces.py
src/collective/smartlink/setuphandlers.py
src/collective/smartlink/testing.py
src/collective/smartlink/behaviors/__init__.py
src/collective/smartlink/behaviors/configure.zcml
src/collective/smartlink/behaviors/interfaces.py
src/collective/smartlink/browser/__init__.py
src/collective/smartlink/browser/configure.zcml
src/collective/smartlink/browser/view.py
src/collective/smartlink/browser/static/.gitkeep
src/collective/smartlink/browser/static/templates/link.pt
src/collective/smartlink/browser/templates/link.pt
src/collective/smartlink/locales/update.sh
src/collective/smartlink/locales/it/LC_MESSAGES/collective.smartlink.po
src/collective/smartlink/locales/it/LC_MESSAGES/plone.po
src/collective/smartlink/profiles/default/browserlayer.xml
src/collective/smartlink/profiles/default/collectivesmartlink_default.txt
src/collective/smartlink/profiles/default/metadata.xml
src/collective/smartlink/profiles/default/types.xml
src/collective/smartlink/profiles/default/types/Link.xml
src/collective/smartlink/profiles/uninstall/browserlayer.xml
src/collective/smartlink/profiles/uninstall/collectivesmartlink_uninstall.txt
src/collective/smartlink/schema/__init__.py
src/collective/smartlink/schema/link.xml
src/collective/smartlink/tests/__init__.py
src/collective/smartlink/tests/test_robot.py
src/collective/smartlink/tests/test_setup.py
src/collective/smartlink/tests/robot/test_example.robot
src/collective/smartlink/transform/__init__.py
src/collective/smartlink/transform/configure.zcml
src/collective/smartlink/transform/transform.py
src/collective/smartlink/upgrades/__init__.py
src/collective/smartlink/upgrades/configure.zcml
src/collective/smartlink/upgrades/remove_internal_link.py
